[{"owner":"mama","name":"AD","done":true,"id":"1652935781644"},{"owner":"mama","name":"adADad","done":true,"id":"1652935789011"},{"owner":"my","name":"tsetse","done":true,"id":"1652935814699"},{"owner":"papa","name":"setstset","done":true,"id":"1652935821635"},{"owner":"papa","name":"stsdgdsg sdg s","done":false,"id":"1652935824251"},{"owner":"my","name":"123123","done":false,"id":"1652936597123"},{"owner":"my","name":"fgdfgb","done":false,"id":"1652936598658"},{"owner":"my","name":"v bn","done":false,"id":"1652936600378"},{"owner":"papa","name":"zxczxczx","done":true,"id":"1652936607314"}]